pretty_bear-0.0.2.data/scripts/oh_bear
prettybear/__init__.py
prettybear/oh_bear.py
pretty_bear-0.0.2.dist-info/LICENSE
pretty_bear-0.0.2.dist-info/METADATA
pretty_bear-0.0.2.dist-info/WHEEL
pretty_bear-0.0.2.dist-info/top_level.txt
pretty_bear-0.0.2.dist-info/RECORD
