Metadata-Version: 2.1
Name: pretty-bear
Version: 0.0.2
Summary: A small example package
Home-page: https://github.com/pypa/sampleproject
Author: lwb
Author-email: lwb@example.com
License: UNKNOWN
Platform: UNKNOWN
Classifier: Programming Language :: Python :: 3
Classifier: License :: OSI Approved :: MIT License
Classifier: Operating System :: OS Independent
Requires-Python: >=3.7
License-File: LICENSE
Requires-Dist: requests (>=2.20.0)
